ModifiedSapGuiLibrary/ModifiedSapGuiLibrary.py
ModifiedSapGuiLibrary/__init__.py
ModifiedSapGuiLibrary/function_timeout.py
ModifiedSapGuiLibrary-1.0.1.dist-info/METADATA
ModifiedSapGuiLibrary-1.0.1.dist-info/WHEEL
ModifiedSapGuiLibrary-1.0.1.dist-info/top_level.txt
ModifiedSapGuiLibrary-1.0.1.dist-info/RECORD
