Metadata-Version: 2.1
Name: ModifiedSapGuiLibrary
Version: 1.0.1
Summary: Modified Package For SapGuiLibrary
Author: IT Dev HOTD Python Developer
Classifier: Programming Language :: Python :: 3
Classifier: License :: OSI Approved :: MIT License
Classifier: Operating System :: OS Independent
Requires-Python: >=3.7
Requires-Dist: keyboard (>=0.13.5)
